djangocms_filer_video-0.1.1.dist-info/RECORD
djangocms_filer_video-0.1.1.dist-info/metadata.json
djangocms_filer_video-0.1.1.dist-info/WHEEL
djangocms_filer_video-0.1.1.dist-info/DESCRIPTION.rst
djangocms_filer_video-0.1.1.dist-info/top_level.txt
djangocms_filer_video-0.1.1.dist-info/METADATA
djangocms_filer_video/tasks.py
djangocms_filer_video/__init__.py
djangocms_filer_video/apps.py
djangocms_filer_video/settings.py
djangocms_filer_video/templatetags/__init__.py
djangocms_filer_video/templatetags/filer_video_tags.py
djangocms_filer_video/migrations/0004_auto_20171123_1311.py
djangocms_filer_video/migrations/0002_videofile_meta_duration_seconds.py
djangocms_filer_video/migrations/__init__.py
djangocms_filer_video/migrations/0003_auto_20171114_1720.py
djangocms_filer_video/migrations/0001_initial.py
djangocms_filer_video/tests/__init__.py
djangocms_filer_video/tests/admin.py
djangocms_filer_video/tests/utils/__init__.py
djangocms_filer_video/admin/videoadmin.py
djangocms_filer_video/admin/__init__.py
djangocms_filer_video/admin/forms.py
djangocms_filer_video/management/__init__.py
djangocms_filer_video/management/commands/run_conversion.py
djangocms_filer_video/management/commands/restart_conversions.py
djangocms_filer_video/management/commands/update_meta.py
djangocms_filer_video/management/commands/generate_missing_conversions.py
djangocms_filer_video/management/commands/update_poster.py
djangocms_filer_video/management/commands/__init__.py
djangocms_filer_video/management/commands/reset_conversions.py
djangocms_filer_video/utils/compat.py
djangocms_filer_video/utils/ffmpeg.py
djangocms_filer_video/utils/__init__.py
djangocms_filer_video/utils/video_formats.py
djangocms_filer_video/models/abstract_models.py
djangocms_filer_video/models/__init__.py
djangocms_filer_video/models/video_models.py
djangocms_filer_video/fields/__init__.py
djangocms_filer_video/fields/video.py
