Metadata-Version: 2.0
Name: djangocms-filer-video
Version: 0.1.1
Summary: Video extension for Django filer.
Home-page: https://github.com/Air-Mark/djangocms-filer-video
Author: Mark Trifonov
Author-email: air.t.mark@gmail.com
License: UNKNOWN
Keywords: django,djangocmsfiler,video
Platform: UNKNOWN
Classifier: Framework :: Django
Classifier: License :: OSI Approved :: MIT License
Classifier: Programming Language :: Python
Classifier: Programming Language :: Python :: 3
Classifier: Topic :: Internet :: WWW/HTTP
Requires-Dist: Django (>=1.8,<=1.11)
